[
   {
      "id": 1,
      "title": "first Post",
      "content": "This is the content of the 1 post.",
      "author": "Othman ele",
      "created_at": "2024-02-18T08:00:00Z",
      "updated_at": "2024-2-18/13:17"
   },
   {
      "id": 2,
      "title": "second Post",
      "content": "This is the content of the 2 post.",
      "author": "Redouane elhamiti",
      "created_at": "2024-02-18T08:00:00Z",
      "updated_at": "2024-2-18/15:4"
   },
   {
      "title": "third Post",
      "content": "This is the content of the third post.",
      "author": "Redouane",
      "created_at": "2024-02-18T08:00:00Z",
      "updated_at": "2024-02-19T09:35:23.945Z",
      "id": 3
   },
   {
      "title": "forth Post",
      "content": "This is the content of the forth post.",
      "author": "Redouane",
      "created_at": "2024-02-13T07:55:00Z",
      "updated_at": "2024-02-19T09:35:50.400Z",
      "id": 4
   },
   {
      "title": "fifth Post",
      "content": "This is the content of the fifth post.",
      "author": "redouane ",
      "updated_at": "2024-2-19/10:1",
      "id": 5,
      "created_at": "2024-02-12T14:25:00Z"
   },
   {
      "title": "sixth Post",
      "content": "This is the content of the sixth post.",
      "author": "Redouane ham",
      "updated_at": "2024-2-19/9:58",
      "id": 6
   },
   {
      "title": "seventh Post",
      "content": "This is the content of the seventh post.",
      "author": "Redouane",
      "id": 7,
      "created_at": "2024-02-19T09:09:33.137Z"
   }
]